nxdb/__init__.py
nxdb/cli.py
nxdb/nxdb.py
NXDB-0.1.0.8.dist-info/METADATA
NXDB-0.1.0.8.dist-info/WHEEL
NXDB-0.1.0.8.dist-info/entry_points.txt
NXDB-0.1.0.8.dist-info/top_level.txt
NXDB-0.1.0.8.dist-info/RECORD
