Metadata-Version: 2.2
Name: NXDB
Version: 0.1.0.8
Author: VladosNX
Author-email: email.name@email.com
Requires-Dist: pyyaml
Dynamic: author
Dynamic: author-email
Dynamic: requires-dist
